script_background_music/__init__.py
script_background_music/context.py
script_background_music/play.py
script_background_music/songs/SOURCES.md
script_background_music/songs/__init__.py
script_background_music/songs/local-forecast.mp3
script_background_music/songs/lofi.mp3
script_background_music/songs/overcast.mp3
script_background_music/vendor/__init__.py
script_background_music/vendor/playsound/LICENSE
script_background_music/vendor/playsound/__init__.py
script_background_music-1.5.10.dist-info/licenses/LICENSE
script_background_music-1.5.10.dist-info/METADATA
script_background_music-1.5.10.dist-info/WHEEL
script_background_music-1.5.10.dist-info/top_level.txt
script_background_music-1.5.10.dist-info/RECORD
