Metadata-Version: 2.4
Name: script-background-music
Version: 1.5.10
Summary: Play elevator music in the background while your script runs.
Author-email: Timo Reymann <mail@timo-reymann.de>
Project-URL: Homepage, https://github.com/timo-reymann/python-script-background-music
Classifier: Development Status :: 5 - Production/Stable
Classifier: Intended Audience :: Developers
Classifier: License :: OSI Approved :: MIT License
Classifier: Programming Language :: Python :: 3
Classifier: Programming Language :: Python :: 3.6
Classifier: Programming Language :: Python :: 3.7
Classifier: Programming Language :: Python :: 3.8
Classifier: Programming Language :: Python :: 3.9
Classifier: Programming Language :: Python :: 3.10
Classifier: Programming Language :: Python :: 3.11
Classifier: Programming Language :: Python :: 3.12
Requires-Python: >=3.8
License-File: LICENSE
Provides-Extra: dev
Requires-Dist: setuptools==80.*; extra == "dev"
Requires-Dist: setuptools-scm==8.*; extra == "dev"
Requires-Dist: twine==6.1.*; extra == "dev"
Requires-Dist: wheel==0.45.*; extra == "dev"
Requires-Dist: pydoctor==25.4.*; extra == "dev"
Requires-Dist: build==1.*; extra == "dev"
Dynamic: license-file
